trustfall-0.2.1.dist-info/METADATA
trustfall-0.2.1.dist-info/WHEEL
trustfall/__init__.py
trustfall/_internals.py
trustfall/_internals.pyi
trustfall/adapter.py
trustfall/execution.py
trustfall/py.typed
trustfall/tests/__init__.py
trustfall/tests/numbers_adapter.py
trustfall/tests/test_execution.py
trustfall/tests/test_schema.py
trustfall/trustfall.cp312-win_amd64.pyd
trustfall-0.2.1.dist-info/RECORD
