Metadata-Version: 2.4
Name: trustfall
Version: 0.2.1
Classifier: Development Status :: 4 - Beta
Classifier: Intended Audience :: Developers
Classifier: License :: OSI Approved :: Apache Software License
Classifier: Programming Language :: Python :: 3
Classifier: Programming Language :: Python :: 3.10
Classifier: Programming Language :: Python :: 3.11
Classifier: Programming Language :: Python :: 3.12
Classifier: Programming Language :: Python :: 3.13
Classifier: Programming Language :: Python :: 3.14
Classifier: Topic :: Database :: Database Engines/Servers
Classifier: Topic :: Software Development :: Compilers
Classifier: Topic :: Software Development :: Interpreters
Classifier: Typing :: Typed
Summary: A query engine for any combination of data sources. Query your files and APIs as if they were databases!
Author: Predrag Gruevski
License: Apache 2.0
Requires-Python: >=3.10
Project-URL: homepage, https://play.predr.ag/
Project-URL: repository, https://github.com/obi1kenobi/trustfall
